medium_crosspost/__init__.py
medium_crosspost/medium_crosspost.py
medium_crosspost/test_medium_crosspost.py
medium_crosspost-0.1.9.dist-info/LICENSE
medium_crosspost-0.1.9.dist-info/METADATA
medium_crosspost-0.1.9.dist-info/WHEEL
medium_crosspost-0.1.9.dist-info/top_level.txt
medium_crosspost-0.1.9.dist-info/RECORD
