Metadata-Version: 2.1
Name: medium-crosspost
Version: 0.1.9
Summary: Easily crosspost articles to Medium
Home-page: https://github.com/typenil/ghost-crosspost-medium
Author: Matt White
Author-email: code@typenil.com
License: MIT License
Keywords: medium ghost crosspost blog zapier
Platform: UNKNOWN
Classifier: Development Status :: 3 - Alpha
Classifier: Environment :: Console
Classifier: Intended Audience :: Developers
Classifier: License :: OSI Approved :: MIT License
Classifier: Natural Language :: English
Classifier: Operating System :: OS Independent
Classifier: Programming Language :: Python
Classifier: Programming Language :: Python :: 3.7
Classifier: Topic :: Utilities
Requires-Dist: requests
